w2n2w/__init__.py
w2n2w-0.3.1.dist-info/LICENSE
w2n2w-0.3.1.dist-info/METADATA
w2n2w-0.3.1.dist-info/WHEEL
w2n2w-0.3.1.dist-info/top_level.txt
w2n2w-0.3.1.dist-info/RECORD
