Metadata-Version: 2.1
Name: w2n2w
Version: 0.3.1
Summary: Convert words to numbers and back again
Home-page: https://github.com/Crozzers/w2n2w
Author: Crozzers
Author-email: captaincrozzers@gmail.com
License: MIT
Keywords: numbers,convert,words
Platform: UNKNOWN
Classifier: Development Status :: 3 - Alpha
Classifier: Intended Audience :: Developers
Classifier: Programming Language :: Python :: 3 :: Only
Requires-Python: >=3.6
License-File: LICENSE
